 <Application>
 
<Header>

  <Version val="14060.00"/>

  <WithIsn val="Y"/>

  <Exe comp="-1"/>

  <LastIsn val="14"/>

  <LastIsnFolder val="0"/>

</Header>

<DataRepositoryProperties/>
 <DataSourceRepository>
  <DataObjects>
 
<DataObject PhysicalName="[TB_OutboundMessages]" Resident="N" UniqueISNConvState="12" data_source="DestinationDB_6_36_288_1" id="1" name="[TB_OutboundMessages]" offset="229" length="12002"/> 
<DataObject PhysicalName="[TB_MessageHeader]" Resident="N" UniqueISNConvState="12" data_source="DestinationDB_7_40_580_1" id="2" name="[TB_MessageHeader]" offset="12232" length="3365"/> 
<DataObject PhysicalName="[RoleCall_Organization_tbl]" Resident="N" UniqueISNConvState="12" data_source="DestinationDB_7_41_98_4" id="3" name="[RoleCall_Organization_tbl]" offset="15598" length="6320"/> 
<DataObject PhysicalName="[RoleCall_Location_Tracker]" Resident="N" UniqueISNConvState="12" data_source="DestinationDB_7_43_66_2" id="4" name="[RoleCall_Location_Tracker]" offset="21919" length="5778"/> 
<DataObject PhysicalName="[TB_OutboundMessages]" Resident="N" UniqueISNConvState="12" data_source="DestinationDB_8_69_157_1" id="5" name="[TB_OutboundMessages]" offset="27698" length="12002"/> 
<DataObject PhysicalName="[TB_OutboundMessages]" Resident="N" UniqueISNConvState="12" data_source="DestinationDB_1_11_141_1" id="6" name="[TB_OutboundMessages]" offset="39701" length="12002"/> 
<DataObject PhysicalName="[RoleCall_Organization_tbl]" Resident="N" UniqueISNConvState="12" data_source="DestinationDB_1_14_98_4" id="7" name="[RoleCall_Organization_tbl]" offset="51704" length="6320"/> 
<DataObject PhysicalName="[RoleCall_COASites_Tracker]" Resident="N" UniqueISNConvState="12" data_source="DestinationDB_1_21_58_2" id="8" name="[RoleCall_COASites_Tracker]" offset="58025" length="5104"/> 
<DataObject PhysicalName="[RoleCall_COASites_Tracker]" Resident="N" UniqueISNConvState="12" data_source="DestinationDB_1_22_58_2" id="9" name="[RoleCall_COASites_Tracker]" offset="63130" length="5104"/> 
<DataObject PhysicalName="[TB_MessageHeader]" Resident="N" UniqueISNConvState="12" data_source="DestinationDB_1_2_243_1" id="10" name="[TB_MessageHeader]" offset="68235" length="2626"/> 
<DataObject PhysicalName="[TB_OutboundMessages]" Resident="N" UniqueISNConvState="12" data_source="DestinationDB_1_35_469_1" id="11" name="[TB_OutboundMessages]" offset="70862" length="12003"/> 
<DataObject PhysicalName="[TB_OutboundMessages]" Resident="N" UniqueISNConvState="12" data_source="DestinationDB_1_35_471_1" id="12" name="[TB_OutboundMessages]" offset="82866" length="12003"/> 
<DataObject PhysicalName="[TB_OutboundMessages]" Resident="N" UniqueISNConvState="12" data_source="DestinationDB_1_35_472_1" id="13" name="[TB_OutboundMessages]" offset="94870" length="12003"/> 
<DataObject PhysicalName="[RoleCall_Location_Tracker]" Resident="N" UniqueISNConvState="12" data_source="DestinationDB_1_72_66_2" id="14" name="[RoleCall_Location_Tracker]" offset="106874" length="6521"/> 
<DataObject PhysicalName="[RoleCall_Location_Tracker]" Resident="N" UniqueISNConvState="12" data_source="DestinationDB_1_72_550_2" id="15" name="[RoleCall_Location_Tracker]" offset="113396" length="6522"/>  </DataObjects>
 </DataSourceRepository>
 <LastModified val="31027888100727792"/>  </Application>
